{"Title":"Combine Our Power! The Mightiest, Final Kamehameha","Year":"2011","Released":"20 Mar 2011","Genre":"Animation, Action, Adventure","Director":"Yasuhiro Nowatari","Writer":"Hiroshi Toda, Akira Toriyama","Actors":"Masako Nozawa, Mayumi Tanaka, Ry\u00F4 Horikawa","Plot":"Super Perfect Cell and Gohan charge their Kamehameha attack for the final confrontation for the fate of the Earth.","Poster":"https://m.media-amazon.com/images/M/MV5BZDBmM2ZiMDctMWE1NS00ZDU2LWE2YmEtOWI1MmQxZTliNzM2XkEyXkFqcGdeQXVyOTA0MzY4MjY@._V1_SX300.jpg","Ratings":[{"Source":"Internet Movie Database","Value":"7.2/10"}],"imdbRating":"7.2","imdbVotes":"1241","imdbID":"tt1856933","Type":"episode","Response":"True","Episode":96}